{
    "sourceFile": "content/post/Gohh/3.Architecture/CSAPP/CSAPP03/index.zh-cn.md",
    "activeCommit": 0,
    "commits": [
        {
            "activePatchIndex": 1,
            "patches": [
                {
                    "date": 1715560923228,
                    "content": "Index: \n===================================================================\n--- \n+++ \n"
                },
                {
                    "date": 1715560939684,
                    "content": "Index: \n===================================================================\n--- \n+++ \n@@ -9,4 +9,5 @@\n math: false\n weight:\n readingTime: true\n ---\n+\n"
                }
            ],
            "date": 1715560923228,
            "name": "Commit-0",
            "content": "---\ntitle: \"三.处理器设计(CSAPP)\"\ndate: 2023-04-09T20:13:06+08:00\ndraft: True\ntags: [CSAPP]\ncategories: [\"CSAPP\",\"CS\"]\nauthor: [\"Yeelight\"]\nshowtoc: true\nmath: false\nweight:\nreadingTime: true\n---\n"
        }
    ]
}